drf_camel_case/__init__.py
drf_camel_case/parser.py
drf_camel_case/render.py
drf_camel_case/settings.py
drf_camel_case/util.py
drf_camel_case-1.0.2.dist-info/AUTHORS.rst
drf_camel_case-1.0.2.dist-info/LICENSE
drf_camel_case-1.0.2.dist-info/METADATA
drf_camel_case-1.0.2.dist-info/WHEEL
drf_camel_case-1.0.2.dist-info/top_level.txt
drf_camel_case-1.0.2.dist-info/RECORD
