Metadata-Version: 2.1
Name: drf-camel-case
Version: 1.0.2
Summary: Camel case JSON support for Django REST framework with orjson.
Home-page: https://github.com/JITdev/drf-camel-case
Author: Roland Kainrath
Author-email: justintimedev@gmail.com
License: BSD
Keywords: drf_camel_case,django rest framework,django
Platform: UNKNOWN
Classifier: Development Status :: 5 - Production/Stable
Classifier: Intended Audience :: Developers
Classifier: License :: OSI Approved :: BSD License
Classifier: Natural Language :: English
Classifier: Programming Language :: Python :: 3
Classifier: Programming Language :: Python :: 3.7
Classifier: Programming Language :: Python :: 3.8
Classifier: Programming Language :: Python :: 3.9
Classifier: Programming Language :: Python :: 3.10
Requires-Python: >=3.7
License-File: LICENSE
License-File: AUTHORS.rst
Requires-Dist: orjson
